model_version_manager/__init__.py
model_version_manager/version.py
model_version_manager-1.0.1.dist-info/METADATA
model_version_manager-1.0.1.dist-info/WHEEL
model_version_manager-1.0.1.dist-info/top_level.txt
model_version_manager-1.0.1.dist-info/RECORD
