Metadata-Version: 2.4
Name: model_version_manager
Version: 1.0.1
Summary: Makes it easier to work with versions for your projects.
Home-page: https://github.com/droid-darkangel/Version
Author: Darkangel
Author-email: llopnin@gmail.com
Classifier: Programming Language :: Python :: 3
Classifier: License :: OSI Approved :: MIT License
Classifier: Operating System :: OS Independent
Requires-Python: >=3.11
Dynamic: author
Dynamic: author-email
Dynamic: classifier
Dynamic: description
Dynamic: description-content-type
Dynamic: home-page
Dynamic: requires-python
Dynamic: summary
